dwarf/__init__.py
dwarf_ml-0.0.1.dist-info/METADATA
dwarf_ml-0.0.1.dist-info/WHEEL
dwarf_ml-0.0.1.dist-info/top_level.txt
dwarf_ml-0.0.1.dist-info/RECORD
