Metadata-Version: 2.1
Name: dwarf-ml
Version: 0.0.1
Summary: DWARF
Author: MAPS
Author-email: dongguk.maps@gmail.com
Keywords: Decision Tree,DT
Classifier: Programming Language :: Python :: 3.7
Classifier: Programming Language :: Python :: 3.8
Classifier: Programming Language :: Python :: 3.9
Requires-Python: >=3.7
Requires-Dist: pandas
